tlc/__init__.py
tlc/__init__.pyi
tlc/client/__init__.py
tlc/client/__init__.pyi
tlc/client/_apply_pillow_patch.py
tlc/client/_apply_pillow_patch.pyi
tlc/client/_ensure_torch.py
tlc/client/_ensure_torch.pyi
tlc/client/bulk_data_url_utils.py
tlc/client/bulk_data_url_utils.pyi
tlc/client/data_format.py
tlc/client/data_format.pyi
tlc/client/helpers.py
tlc/client/helpers.pyi
tlc/client/log.py
tlc/client/log.pyi
tlc/client/sample_type.py
tlc/client/sample_type.pyi
tlc/client/session.py
tlc/client/session.pyi
tlc/client/utils.py
tlc/client/utils.pyi
tlc/client/operations/__init__.py
tlc/client/operations/__init__.pyi
tlc/client/operations/table_operations.py
tlc/client/operations/table_operations.pyi
tlc/client/reduce/__init__.py
tlc/client/reduce/__init__.pyi
tlc/client/reduce/pacmap.py
tlc/client/reduce/pacmap.pyi
tlc/client/reduce/reduce.py
tlc/client/reduce/reduce.pyi
tlc/client/reduce/reduction_method.py
tlc/client/reduce/reduction_method.pyi
tlc/client/reduce/umap.py
tlc/client/reduce/umap.pyi
tlc/client/torch/__init__.py
tlc/client/torch/__init__.pyi
tlc/client/torch/utils.py
tlc/client/torch/utils.pyi
tlc/client/torch/metrics/__init__.py
tlc/client/torch/metrics/__init__.pyi
tlc/client/torch/metrics/collect.py
tlc/client/torch/metrics/collect.pyi
tlc/client/torch/metrics/collect_dataset.py
tlc/client/torch/metrics/collect_dataset.pyi
tlc/client/torch/metrics/predictor.py
tlc/client/torch/metrics/predictor.pyi
tlc/client/torch/metrics/metrics_aggregators/__init__.py
tlc/client/torch/metrics/metrics_aggregators/__init__.pyi
tlc/client/torch/metrics/metrics_aggregators/aggregator.py
tlc/client/torch/metrics/metrics_aggregators/aggregator.pyi
tlc/client/torch/metrics/metrics_aggregators/mean_aggregator.py
tlc/client/torch/metrics/metrics_aggregators/mean_aggregator.pyi
tlc/client/torch/metrics/metrics_collectors/__init__.py
tlc/client/torch/metrics/metrics_collectors/__init__.pyi
tlc/client/torch/metrics/metrics_collectors/_composite_metrics_collector.py
3lc-2.21.3.dist-info/METADATA
3lc-2.21.3.dist-info/WHEEL
3lc-2.21.3.dist-info/entry_points.txt
3lc-2.21.3.dist-info/RECORD
